bcex/__init__.py
bcex/core/__init__.py
bcex/core/bcex_interface.py
bcex/core/order_response.py
bcex/core/orders.py
bcex/core/symbol.py
bcex/core/trade.py
bcex/core/utils.py
bcex/core/websocket_client.py
bcex/examples/__init__.py
bcex/examples/quote_both_sides.py
bcex/examples/simple_strategy.py
bcex/examples/trader.py
bcex-1.0.1.dist-info/LICENSE
bcex-1.0.1.dist-info/METADATA
bcex-1.0.1.dist-info/WHEEL
bcex-1.0.1.dist-info/top_level.txt
bcex-1.0.1.dist-info/RECORD
