Metadata-Version: 2.1
Name: bcex
Version: 1.0.1
Summary: Websocket Client and interface for Blockchain.com Exchange
Home-page: https://github.com/simon-bc/bcex
Author: simon-bc
Author-email: simon@blockchain.com
License: UNKNOWN
Keywords: cryptocurrency,bitcoin,btc,trading,market feed,market data,exchange,blockchain,eth,xlm,crypto,market making,bot
Platform: UNKNOWN
Classifier: Programming Language :: Python :: 3
Classifier: License :: OSI Approved :: MIT License
Classifier: Operating System :: OS Independent
Requires-Python: >=3.6
Requires-Dist: numpy
Requires-Dist: websocket-client
Requires-Dist: sortedcontainers
Requires-Dist: iso8601
Requires-Dist: pytz
